MANIFEST.in
README
__init__.py
__pkginfo__.py
entities.py
hooks.py
recipes.py
schema.py
setup.py
site_cubicweb.py
_apycotlib/__init__.py
_apycotlib/atest.py
_apycotlib/repositories.py
_apycotlib/writer.py
_apycotlib/checkers/__init__.py
_apycotlib/checkers/jslint.py
_apycotlib/checkers/python.py
_apycotlib/preprocessors/__init__.py
_apycotlib/preprocessors/distutils.py
apycot.egg-info/PKG-INFO
apycot.egg-info/SOURCES.txt
apycot.egg-info/dependency_links.txt
apycot.egg-info/requires.txt
apycot.egg-info/top_level.txt
data/cubes.apycot.css
data/cubes.apycot.js
data/feed-logo.png
data/feed-logo.svg
doc/apycot_processes_en.dia
ext/jslint.js
i18n/en.po
i18n/es.po
i18n/fr.po
migration/1.0.1_Any.py
migration/1.0.4_Any.py
migration/1.0.7_Any.py
migration/1.2.0_Any.py
migration/1.3.0_Any.py
migration/1.4.0_Any.py
migration/1.4.1_Any.py
migration/1.4.3_Any.py
migration/1.5.0_Any.py
migration/1.6.0_Any.py
migration/1.9.0_Any.py
migration/2.0.0_Any.py
migration/2.0.1_Any.py
migration/2.0.5_Any.py
migration/2.1.0_Any.py
migration/2.1.2_Any.py
migration/2.2.1_Any.py
migration/create_recipes.py
migration/postcreate.py
narval/apycot.py
test/test_apycot.py
views/__init__.py
views/facets.py
views/primary.py
views/reports.py
views/rss.py
views/testexecution.py
views/tracker.py
wdoc/ChangeLog_en
wdoc/ChangeLog_fr
wdoc/apycot_automation_en.rst
wdoc/apycot_checker_en.rst
wdoc/apycot_en.rst
wdoc/apycot_links_en.rst
wdoc/apycot_step_by_step_fr.rst
wdoc/apycot_test_configuration_en.rst
wdoc/toc.xml
wdoc/images/apycot_processes_en.png