Metadata-Version: 1.0
Name: apycot
Version: 2.2.1
Summary: Continuous testing / integration tool for the CubicWeb framework
Home-page: http://www.logilab.org/project/apycot
Author: Logilab
Author-email: contact@logilab.fr
License: GPL
Platform: UNKNOWN
